dice_api/__init__.py
dice_api/app.py
dice_api/cli.py
dice_api/host.py
dice_api/py.typed
dice_api/storage/__init__.py
dice_api/storage/_hdfs.py
dice_api-2025.3.1.dist-info/METADATA
dice_api-2025.3.1.dist-info/WHEEL
dice_api-2025.3.1.dist-info/entry_points.txt
dice_api-2025.3.1.dist-info/licenses/LICENSE
dice_api-2025.3.1.dist-info/RECORD
